{"pkgs":{"@mekstuff-rbxts/task-scheduler":{"signature":"XfM2I4O7SAzoOqsZnUwCsUjV8Ig=3a419db88c1339ea0ce9","version":"^0.1.0","version_resolve":"0.1.0"},"@mekstuff-rbxts/core":{"signature":"wV_yxwEp4FR960kQMvQ0keHh4DI=914103163d203ae6616f","version":"^0.1.5","version_resolve":"0.1.5"},"@mekstuff-rbxts/rig-builder":{"signature":"ef7t893MyRcfAgJOKJrYtTK7lgs=93a271b5dccdd53fcf5c","version":"^1.0.0","version_resolve":"1.0.0"},"@mekstuff-rbxts/path-computing-service":{"signature":"F1WdqOZ94foJAHTMTwXgiq7BS7M=7fc4900d2b2631c6032d","version":"^0.1.3","version_resolve":"0.1.3"}},"tree":{"@mekstuff-rbxts/task-scheduler@0.1.0>>@mekstuff-rbxts/core@0.1.5":"wV_yxwEp4FR960kQMvQ0keHh4DI=914103163d203ae6616f","@mekstuff-rbxts/core@0.1.5>>@mekstuff-rbxts/threader@0.1.0":"qiDXH2N6FsAqAPeRtxLthc7inPo=9de0300f40596b59dd2a","@mekstuff-rbxts/task-scheduler@0.1.0>>@mekstuff-rbxts/servant@0.1.5":"dIg96hTKw_FR+7rofORj86bgj78=ded8d6dedfc7619eb183","@mekstuff-rbxts/servant@0.1.5>>@mekstuff-rbxts/core@0.1.5":"wV_yxwEp4FR960kQMvQ0keHh4DI=914103163d203ae6616f","@mekstuff-rbxts/task-scheduler@0.1.0>>@mekstuff-rbxts/signal@0.1.7":"qCdMoxB1vSNAvfeOdgcFbtWbrv0=0f7aa697bf1bc3ea8f31","@mekstuff-rbxts/signal@0.1.7>>@mekstuff-rbxts/core@0.1.5":"wV_yxwEp4FR960kQMvQ0keHh4DI=914103163d203ae6616f","@mekstuff-rbxts/path-computing-service@0.1.3>>@mekstuff-rbxts/core@0.1.5":"wV_yxwEp4FR960kQMvQ0keHh4DI=914103163d203ae6616f","@mekstuff-rbxts/path-computing-service@0.1.3>>@mekstuff-rbxts/signal@0.1.7":"qCdMoxB1vSNAvfeOdgcFbtWbrv0=0f7aa697bf1bc3ea8f31"},"version":"0"}